setup.py
rectangle_overlap/__init__.py
rectangle_overlap/check.py
rectangle_overlap/exmples.py
rectangle_overlap.egg-info/PKG-INFO
rectangle_overlap.egg-info/SOURCES.txt
rectangle_overlap.egg-info/dependency_links.txt
rectangle_overlap.egg-info/not-zip-safe
rectangle_overlap.egg-info/top_level.txt