Metadata-Version: 1.0
Name: rectangle-overlap
Version: 0.2
Summary: Overlapping rectangles
Home-page: http://github.com/storborg/funniest
Author: Asterios Vounotrypidis
Author-email: avounotr@gmail.com
License: MIT
Platform: UNKNOWN
